{
    "openDungeonNum": 1,
    "currentCount": [
        0,
        0,
        0,
        0,
        0,
        0,
        0,
        0,
        0,
        0,
        0,
        0,
        0,
        0,
        0,
        0,
        0,
        0,
        0
    ],
    "isFind": [
        false,
        false,
        false,
        false,
        true,
        false,
        false,
        false,
        false,
        true,
        false,
        false,
        false,
        false,
        false,
        false,
        false,
        true,
        false
    ],
    "enhance": [
        0,
        0,
        0,
        0,
        1,
        0,
        0,
        0,
        0,
        0,
        0,
        0,
        0,
        0,
        0,
        0,
        0,
        0,
        0
    ],
    "LobbyDeck": [
        {
            "instanceID": 32840
        },
        {
            "instanceID": 32840
        },
        {
            "instanceID": 32840
        },
        {
            "instanceID": 34518
        },
        {
            "instanceID": 34518
        },
        {
            "instanceID": 34518
        }
    ],
    "currentCrystal": 99999514
}